<?xml version="1.0"?>
<!DOCTYPE source_file SYSTEM "apf.v4.0.1.dtd">
<source_file URI="CTV20001205.1330.0213.sgm" SOURCE="broadcast news" TYPE="text" VERSION="4.0" AUTHOR="LDC" ENCODING="UTF-8">
<document DOCID="CTV20001205.1330.0213">
<entity ID="CTV20001205.1330.0213-E1" TYPE="GPE" SUBTYPE="Nation" CLASS="SPC">
  <entity_mention ID="1-3" TYPE="NAM" LDCTYPE="NAM" ROLE="GPE">
    <extent>
      <charseq START="145" END="146">美国</charseq>
    </extent>
    <head>
      <charseq START="145" END="146">美国</charseq>
    </head>
  </entity_mention>
  <entity_mention ID="1-32" TYPE="NAM" LDCTYPE="NAM" ROLE="GPE">
    <extent>
      <charseq START="302" END="303">美国</charseq>
    </extent>
    <head>
      <charseq START="302" END="303">美国</charseq>
    </head>
  </entity_mention>
  <entity_attributes>
    <name>
      <charseq START="302" END="303">美国</charseq>
    </name>
    <name>
      <charseq START="145" END="146">美国</charseq>
    </name>
  </entity_attributes>
</entity>
<entity ID="CTV20001205.1330.0213-E2" TYPE="GPE" SUBTYPE="Nation" CLASS="SPC">
  <entity_mention ID="2-4" TYPE="NAM" LDCTYPE="NAM" ROLE="GPE">
    <extent>
      <charseq START="148" END="150">俄罗斯</charseq>
    </extent>
    <head>
      <charseq START="148" END="150">俄罗斯</charseq>
    </head>
  </entity_mention>
  <entity_mention ID="2-33" TYPE="NAM" LDCTYPE="NAM" ROLE="GPE">
    <extent>
      <charseq START="305" END="307">俄罗斯</charseq>
    </extent>
    <head>
      <charseq START="305" END="307">俄罗斯</charseq>
    </head>
  </entity_mention>
  <entity_attributes>
    <name>
      <charseq START="305" END="307">俄罗斯</charseq>
    </name>
    <name>
      <charseq START="148" END="150">俄罗斯</charseq>
    </name>
  </entity_attributes>
</entity>
<entity ID="CTV20001205.1330.0213-E3" TYPE="GPE" SUBTYPE="Nation" CLASS="SPC">
  <entity_mention ID="3-5" TYPE="NAM" LDCTYPE="NAM" ROLE="GPE">
    <extent>
      <charseq START="152" END="154">英
国</charseq>
    </extent>
    <head>
      <charseq START="152" END="154">英
国</charseq>
    </head>
  </entity_mention>
  <entity_mention ID="3-34" TYPE="NAM" LDCTYPE="NAM" ROLE="GPE">
    <extent>
      <charseq START="309" END="310">英国</charseq>
    </extent>
    <head>
      <charseq START="309" END="310">英国</charseq>
    </head>
  </entity_mention>
  <entity_attributes>
    <name>
      <charseq START="152" END="154">英
国</charseq>
    </name>
    <name>
      <charseq START="309" END="310">英国</charseq>
    </name>
  </entity_attributes>
</entity>
<entity ID="CTV20001205.1330.0213-E4" TYPE="GPE" SUBTYPE="Nation" CLASS="SPC">
  <entity_mention ID="4-6" TYPE="NAM" LDCTYPE="NAM" ROLE="GPE">
    <extent>
      <charseq START="156" END="157">法国</charseq>
    </extent>
    <head>
      <charseq START="156" END="157">法国</charseq>
    </head>
  </entity_mention>
  <entity_mention ID="4-35" TYPE="NAM" LDCTYPE="NAM" ROLE="GPE">
    <extent>
      <charseq START="312" END="313">法国</charseq>
    </extent>
    <head>
      <charseq START="312" END="313">法国</charseq>
    </head>
  </entity_mention>
  <entity_attributes>
    <name>
      <charseq START="156" END="157">法国</charseq>
    </name>
    <name>
      <charseq START="312" END="313">法国</charseq>
    </name>
  </entity_attributes>
</entity>
<entity ID="CTV20001205.1330.0213-E5" TYPE="PER" CLASS="SPC">
  <entity_mention ID="5-8" TYPE="NAM" LDCTYPE="NAM" LDCATR="FALSE">
    <extent>
      <charseq START="179" END="180">安南</charseq>
    </extent>
    <head>
      <charseq START="179" END="180">安南</charseq>
    </head>
  </entity_mention>
  <entity_mention ID="5-9" TYPE="NOM" LDCTYPE="NOM" LDCATR="TRUE">
    <extent>
      <charseq START="173" END="178">联合国秘书长</charseq>
    </extent>
    <head>
      <charseq START="176" END="178">秘书长</charseq>
    </head>
  </entity_mention>
  <entity_mention ID="5-40" TYPE="NAM" LDCTYPE="NAM" LDCATR="FALSE">
    <extent>
      <charseq START="340" END="341">安南</charseq>
    </extent>
    <head>
      <charseq START="340" END="341">安南</charseq>
    </head>
  </entity_mention>
  <entity_mention ID="5-52" TYPE="NAM" LDCTYPE="NAM" LDCATR="FALSE">
    <extent>
      <charseq START="408" END="409">安南</charseq>
    </extent>
    <head>
      <charseq START="408" END="409">安南</charseq>
    </head>
  </entity_mention>
  <entity_mention ID="5-53" TYPE="NOM" LDCTYPE="NOM" LDCATR="TRUE">
    <extent>
      <charseq START="402" END="407">联合国秘书长</charseq>
    </extent>
    <head>
      <charseq START="405" END="407">秘书长</charseq>
    </head>
  </entity_mention>
  <entity_mention ID="5-95" TYPE="NOM" LDCTYPE="NOM" LDCATR="TRUE">
    <extent>
      <charseq START="333" END="339">联
合国秘书长</charseq>
    </extent>
    <head>
      <charseq START="337" END="339">秘书长</charseq>
    </head>
  </entity_mention>
  <entity_attributes>
    <name>
      <charseq START="179" END="180">安南</charseq>
    </name>
    <name>
      <charseq START="340" END="341">安南</charseq>
    </name>
    <name>
      <charseq START="408" END="409">安南</charseq>
    </name>
  </entity_attributes>
</entity>
<entity ID="CTV20001205.1330.0213-E7" TYPE="ORG" SUBTYPE="Other" CLASS="SPC">
  <entity_mention ID="7-10" TYPE="NAM" LDCTYPE="NAM">
    <extent>
      <charseq START="173" END="175">联合国</charseq>
    </extent>
    <head>
      <charseq START="173" END="175">联合国</charseq>
    </head>
  </entity_mention>
  <entity_mention ID="7-37" TYPE="NAM" LDCTYPE="NAM">
    <extent>
      <charseq START="316" END="318">联合国</charseq>
    </extent>
    <head>
      <charseq START="316" END="318">联合国</charseq>
    </head>
  </entity_mention>
  <entity_mention ID="7-42" TYPE="NAM" LDCTYPE="NAM">
    <extent>
      <charseq START="333" END="336">联
合国</charseq>
    </extent>
    <head>
      <charseq START="333" END="336">联
合国</charseq>
    </head>
  </entity_mention>
  <entity_mention ID="7-54" TYPE="NAM" LDCTYPE="NAM">
    <extent>
      <charseq START="402" END="404">联合国</charseq>
    </extent>
    <head>
      <charseq START="402" END="404">联合国</charseq>
    </head>
  </entity_mention>
  <entity_attributes>
    <name>
      <charseq START="173" END="175">联合国</charseq>
    </name>
    <name>
      <charseq START="316" END="318">联合国</charseq>
    </name>
    <name>
      <charseq START="333" END="336">联
合国</charseq>
    </name>
    <name>
      <charseq START="402" END="404">联合国</charseq>
    </name>
  </entity_attributes>
</entity>
<entity ID="CTV20001205.1330.0213-E9" TYPE="PER" CLASS="SPC">
  <entity_mention ID="9-19" TYPE="NOM" LDCTYPE="NOM">
    <extent>
      <charseq START="250" END="254">江泽民主席</charseq>
    </extent>
    <head>
      <charseq START="253" END="254">主席</charseq>
    </head>
  </entity_mention>
  <entity_mention ID="9-20" TYPE="NAM" LDCTYPE="NAM">
    <extent>
      <charseq START="250" END="252">江泽民</charseq>
    </extent>
    <head>
      <charseq START="250" END="252">江泽民</charseq>
    </head>
  </entity_mention>
  <entity_attributes>
    <name>
      <charseq START="250" END="252">江泽民</charseq>
    </name>
  </entity_attributes>
</entity>
<entity ID="CTV20001205.1330.0213-E10" TYPE="PER" CLASS="SPC">
  <entity_mention ID="10-21" TYPE="NOM" LDCTYPE="NOM">
    <extent>
      <charseq START="256" END="261">钱其琛副总理</charseq>
    </extent>
    <head>
      <charseq START="259" END="261">副总理</charseq>
    </head>
  </entity_mention>
  <entity_mention ID="10-22" TYPE="NAM" LDCTYPE="NAM">
    <extent>
      <charseq START="256" END="258">钱其琛</charseq>
    </extent>
    <head>
      <charseq START="256" END="258">钱其琛</charseq>
    </head>
  </entity_mention>
  <entity_attributes>
    <name>
      <charseq START="256" END="258">钱其琛</charseq>
    </name>
  </entity_attributes>
</entity>
<entity ID="CTV20001205.1330.0213-E11" TYPE="PER" CLASS="SPC">
  <entity_mention ID="11-23" TYPE="NOM" LDCTYPE="NOM">
    <extent>
      <charseq START="264" END="268">唐家璇外长</charseq>
    </extent>
    <head>
      <charseq START="267" END="268">外长</charseq>
    </head>
  </entity_mention>
  <entity_mention ID="11-24" TYPE="NAM" LDCTYPE="NAM">
    <extent>
      <charseq START="264" END="266">唐家璇</charseq>
    </extent>
    <head>
      <charseq START="264" END="266">唐家璇</charseq>
    </head>
  </entity_mention>
  <entity_mention ID="11-27" TYPE="NOM" LDCTYPE="NOM">
    <extent>
      <charseq START="293" END="297">唐家璇外长</charseq>
    </extent>
    <head>
      <charseq START="296" END="297">外长</charseq>
    </head>
  </entity_mention>
  <entity_mention ID="11-28" TYPE="NAM" LDCTYPE="NAM">
    <extent>
      <charseq START="293" END="295">唐家璇</charseq>
    </extent>
    <head>
      <charseq START="293" END="295">唐家璇</charseq>
    </head>
  </entity_mention>
  <entity_mention ID="11-48" TYPE="NOM" LDCTYPE="NOM">
    <extent>
      <charseq START="370" END="374">唐家璇外长</charseq>
    </extent>
    <head>
      <charseq START="373" END="374">外长</charseq>
    </head>
  </entity_mention>
  <entity_mention ID="11-49" TYPE="NAM" LDCTYPE="NAM">
    <extent>
      <charseq START="370" END="372">唐家璇</charseq>
    </extent>
    <head>
      <charseq START="370" END="372">唐家璇</charseq>
    </head>
  </entity_mention>
  <entity_attributes>
    <name>
      <charseq START="264" END="266">唐家璇</charseq>
    </name>
    <name>
      <charseq START="293" END="295">唐家璇</charseq>
    </name>
    <name>
      <charseq START="370" END="372">唐家璇</charseq>
    </name>
  </entity_attributes>
</entity>
<entity ID="CTV20001205.1330.0213-E12" TYPE="GPE" SUBTYPE="Nation" CLASS="SPC">
  <entity_mention ID="12-30" TYPE="NOM" LDCTYPE="NOM" ROLE="GPE" LDCATR="FALSE">
    <extent>
      <charseq START="302" END="327">美国、俄罗斯、英国、法国四个联合国安理会的常任理事国</charseq>
    </extent>
    <head>
      <charseq START="325" END="327">理事国</charseq>
    </head>
  </entity_mention>
  <entity_mention ID="12-115" TYPE="NOM" LDCTYPE="NOM" ROLE="GPE" LDCATR="TRUE">
    <extent>
      <charseq START="158" END="168">这四个安理会常任理事国</charseq>
    </extent>
    <head>
      <charseq START="166" END="168">理事国</charseq>
    </head>
  </entity_mention>
</entity>
<entity ID="CTV20001205.1330.0213-E13" TYPE="ORG" SUBTYPE="Other" CLASS="SPC">
  <entity_mention ID="13-36" TYPE="NAM" LDCTYPE="NAM">
    <extent>
      <charseq START="316" END="321">联合国安理会</charseq>
    </extent>
    <head>
      <charseq START="319" END="321">安理会</charseq>
    </head>
  </entity_mention>
  <entity_mention ID="13-38" TYPE="NAM" LDCTYPE="NAM">
    <extent>
      <charseq START="161" END="163">安理会</charseq>
    </extent>
    <head>
      <charseq START="161" END="163">安理会</charseq>
    </head>
  </entity_mention>
  <entity_attributes>
    <name>
      <charseq START="319" END="321">安理会</charseq>
    </name>
    <name>
      <charseq START="161" END="163">安理会</charseq>
    </name>
  </entity_attributes>
</entity>
<entity ID="CTV20001205.1330.0213-E14" TYPE="GPE" SUBTYPE="Nation" CLASS="SPC">
  <entity_mention ID="14-41" TYPE="PRO" LDCTYPE="PRO" ROLE="ORG">
    <extent>
      <charseq START="203" END="204">各方</charseq>
    </extent>
    <head>
      <charseq START="203" END="204">各方</charseq>
    </head>
  </entity_mention>
</entity>
<entity ID="CTV20001205.1330.0213-E15" TYPE="PER" CLASS="SPC">
  <entity_mention ID="15-1" TYPE="NOM" LDCTYPE="NOM">
    <extent>
      <charseq START="65" END="70">吴邦国副总理</charseq>
    </extent>
    <head>
      <charseq START="68" END="70">副总理</charseq>
    </head>
  </entity_mention>
  <entity_mention ID="15-93" TYPE="NAM" LDCTYPE="NAM">
    <extent>
      <charseq START="65" END="67">吴邦国</charseq>
    </extent>
    <head>
      <charseq START="65" END="67">吴邦国</charseq>
    </head>
  </entity_mention>
  <entity_attributes>
    <name>
      <charseq START="65" END="67">吴邦国</charseq>
    </name>
  </entity_attributes>
</entity>
<entity ID="CTV20001205.1330.0213-E16" TYPE="GPE" SUBTYPE="Nation" CLASS="SPC">
  <entity_mention ID="16-56" TYPE="NOM" LDCTYPE="NOM" ROLE="GPE">
    <extent>
      <charseq START="432" END="436">有关的国家</charseq>
    </extent>
    <head>
      <charseq START="435" END="436">国家</charseq>
    </head>
  </entity_mention>
</entity>
<entity ID="CTV20001205.1330.0213-E17" TYPE="GPE" SUBTYPE="Nation" CLASS="SPC">
  <entity_mention ID="17-59" TYPE="NOM" LDCTYPE="NOM" ROLE="PER">
    <extent>
      <charseq START="470" END="483">印、巴和克什米尔地区三方人民</charseq>
    </extent>
    <head>
      <charseq START="482" END="483">人民</charseq>
    </head>
  </entity_mention>
</entity>
<entity ID="CTV20001205.1330.0213-E18" TYPE="GPE" SUBTYPE="Nation" CLASS="SPC">
  <entity_mention ID="18-86" TYPE="NOM" LDCTYPE="NOM" ROLE="GPE">
    <extent>
      <charseq START="644" END="645">地区</charseq>
    </extent>
    <head>
      <charseq START="644" END="645">地区</charseq>
    </head>
  </entity_mention>
  <entity_mention ID="18-97" TYPE="NOM" LDCTYPE="NOM" ROLE="GPE">
    <extent>
      <charseq START="470" END="481">印、巴和克什米尔地区三方</charseq>
    </extent>
    <head>
      <charseq START="480" END="481">三方</charseq>
    </head>
  </entity_mention>
</entity>
<entity ID="CTV20001205.1330.0213-E19" TYPE="GPE" SUBTYPE="Nation" CLASS="SPC">
  <entity_mention ID="19-62" TYPE="NAM" LDCTYPE="NAM" ROLE="GPE">
    <extent>
      <charseq START="470" END="470">印</charseq>
    </extent>
    <head>
      <charseq START="470" END="470">印</charseq>
    </head>
  </entity_mention>
  <entity_mention ID="19-77" TYPE="NAM" LDCTYPE="NAM" ROLE="ORG">
    <extent>
      <charseq START="578" END="579">印度</charseq>
    </extent>
    <head>
      <charseq START="578" END="579">印度</charseq>
    </head>
  </entity_mention>
  <entity_mention ID="19-84" TYPE="NAM" LDCTYPE="NAM" ROLE="GPE">
    <extent>
      <charseq START="634" END="634">印</charseq>
    </extent>
    <head>
      <charseq START="634" END="634">印</charseq>
    </head>
  </entity_mention>
  <entity_mention ID="19-98" TYPE="NAM" LDCTYPE="NAM" ROLE="GPE">
    <extent>
      <charseq START="660" END="660">印</charseq>
    </extent>
    <head>
      <charseq START="660" END="660">印</charseq>
    </head>
  </entity_mention>
  <entity_attributes>
    <name>
      <charseq START="470" END="470">印</charseq>
    </name>
    <name>
      <charseq START="578" END="579">印度</charseq>
    </name>
    <name>
      <charseq START="634" END="634">印</charseq>
    </name>
    <name>
      <charseq START="660" END="660">印</charseq>
    </name>
  </entity_attributes>
</entity>
<entity ID="CTV20001205.1330.0213-E20" TYPE="PER" CLASS="SPC">
  <entity_mention ID="20-14" TYPE="NAM" LDCTYPE="NAM" LDCATR="FALSE">
    <extent>
      <charseq START="239" END="244">塔里克阿齐兹</charseq>
    </extent>
    <head>
      <charseq START="239" END="244">塔里克阿齐兹</charseq>
    </head>
  </entity_mention>
  <entity_mention ID="20-15" TYPE="NOM" LDCTYPE="NOM" LDCATR="TRUE">
    <extent>
      <charseq START="233" END="238">伊拉克副总理</charseq>
    </extent>
    <head>
      <charseq START="236" END="238">副总理</charseq>
    </head>
  </entity_mention>
  <entity_mention ID="20-25" TYPE="PRO" LDCTYPE="PRO" LDCATR="FALSE">
    <extent>
      <charseq START="277" END="277">他</charseq>
    </extent>
    <head>
      <charseq START="277" END="277">他</charseq>
    </head>
  </entity_mention>
  <entity_mention ID="20-45" TYPE="NAM" LDCTYPE="NAM" LDCATR="FALSE">
    <extent>
      <charseq START="355" END="357">阿齐兹</charseq>
    </extent>
    <head>
      <charseq START="355" END="357">阿齐兹</charseq>
    </head>
  </entity_mention>
  <entity_mention ID="20-96" TYPE="NOM" LDCTYPE="NOM" LDCATR="TRUE">
    <extent>
      <charseq START="349" END="354">伊拉克副总理</charseq>
    </extent>
    <head>
      <charseq START="352" END="354">副总理</charseq>
    </head>
  </entity_mention>
  <entity_attributes>
    <name>
      <charseq START="239" END="244">塔里克阿齐兹</charseq>
    </name>
    <name>
      <charseq START="355" END="357">阿齐兹</charseq>
    </name>
  </entity_attributes>
</entity>
<entity ID="CTV20001205.1330.0213-E21" TYPE="GPE" SUBTYPE="Nation" CLASS="SPC">
  <entity_mention ID="21-63" TYPE="NAM" LDCTYPE="NAM" ROLE="GPE">
    <extent>
      <charseq START="472" END="472">巴</charseq>
    </extent>
    <head>
      <charseq START="472" END="472">巴</charseq>
    </head>
  </entity_mention>
  <entity_mention ID="21-70" TYPE="NOM" LDCTYPE="NOM" ROLE="ORG">
    <extent>
      <charseq START="530" END="535">巴基斯坦政府</charseq>
    </extent>
    <head>
      <charseq START="534" END="535">政府</charseq>
    </head>
  </entity_mention>
  <entity_mention ID="21-71" TYPE="NAM" LDCTYPE="NAM" ROLE="GPE">
    <extent>
      <charseq START="530" END="533">巴基斯坦</charseq>
    </extent>
    <head>
      <charseq START="530" END="533">巴基斯坦</charseq>
    </head>
  </entity_mention>
  <entity_mention ID="21-74" TYPE="NAM" LDCTYPE="NAM" ROLE="ORG">
    <extent>
      <charseq START="554" END="557">巴基斯坦</charseq>
    </extent>
    <head>
      <charseq START="554" END="557">巴基斯坦</charseq>
    </head>
  </entity_mention>
  <entity_mention ID="21-75" TYPE="NOM" LDCTYPE="NOM" ROLE="GPE">
    <extent>
      <charseq START="550" END="551">巴方</charseq>
    </extent>
    <head>
      <charseq START="551" END="551">方</charseq>
    </head>
  </entity_mention>
  <entity_mention ID="21-76" TYPE="NAM" LDCTYPE="NAM" ROLE="GPE">
    <extent>
      <charseq START="550" END="550">巴</charseq>
    </extent>
    <head>
      <charseq START="550" END="550">巴</charseq>
    </head>
  </entity_mention>
  <entity_mention ID="21-85" TYPE="NAM" LDCTYPE="NAM" ROLE="GPE">
    <extent>
      <charseq START="636" END="636">巴</charseq>
    </extent>
    <head>
      <charseq START="636" END="636">巴</charseq>
    </head>
  </entity_mention>
  <entity_mention ID="21-99" TYPE="NAM" LDCTYPE="NAM" ROLE="GPE">
    <extent>
      <charseq START="662" END="662">巴</charseq>
    </extent>
    <head>
      <charseq START="662" END="662">巴</charseq>
    </head>
  </entity_mention>
  <entity_attributes>
    <name>
      <charseq START="472" END="472">巴</charseq>
    </name>
    <name>
      <charseq START="530" END="533">巴基斯坦</charseq>
    </name>
    <name>
      <charseq START="554" END="557">巴基斯坦</charseq>
    </name>
    <name>
      <charseq START="550" END="550">巴</charseq>
    </name>
    <name>
      <charseq START="636" END="636">巴</charseq>
    </name>
    <name>
      <charseq START="662" END="662">巴</charseq>
    </name>
  </entity_attributes>
</entity>
<entity ID="CTV20001205.1330.0213-E22" TYPE="GPE" SUBTYPE="Population-Center" CLASS="SPC">
  <entity_mention ID="22-64" TYPE="NOM" LDCTYPE="NOM" ROLE="GPE">
    <extent>
      <charseq START="474" END="479">克什米尔地区</charseq>
    </extent>
    <head>
      <charseq START="478" END="479">地区</charseq>
    </head>
  </entity_mention>
  <entity_mention ID="22-65" TYPE="NAM" LDCTYPE="NAM" ROLE="LOC">
    <extent>
      <charseq START="474" END="477">克什米尔</charseq>
    </extent>
    <head>
      <charseq START="474" END="477">克什米尔</charseq>
    </head>
  </entity_mention>
  <entity_mention ID="22-66" TYPE="NAM" LDCTYPE="NAM" ROLE="GPE">
    <extent>
      <charseq START="496" END="499">克什米尔</charseq>
    </extent>
    <head>
      <charseq START="496" END="499">克什米尔</charseq>
    </head>
  </entity_mention>
  <entity_mention ID="22-72" TYPE="NAM" LDCTYPE="NAM" ROLE="GPE">
    <extent>
      <charseq START="543" END="546">克什米尔</charseq>
    </extent>
    <head>
      <charseq START="543" END="546">克什米尔</charseq>
    </head>
  </entity_mention>
  <entity_mention ID="22-78" TYPE="NAM" LDCTYPE="NAM" ROLE="GPE">
    <extent>
      <charseq START="581" END="584">克什米尔</charseq>
    </extent>
    <head>
      <charseq START="581" END="584">克什米尔</charseq>
    </head>
  </entity_mention>
  <entity_mention ID="22-81" TYPE="NAM" LDCTYPE="NAM" ROLE="GPE">
    <extent>
      <charseq START="603" END="607">克
什米尔</charseq>
    </extent>
    <head>
      <charseq START="603" END="607">克
什米尔</charseq>
    </head>
  </entity_mention>
  <entity_attributes>
    <name>
      <charseq START="474" END="477">克什米尔</charseq>
    </name>
    <name>
      <charseq START="496" END="499">克什米尔</charseq>
    </name>
    <name>
      <charseq START="543" END="546">克什米尔</charseq>
    </name>
    <name>
      <charseq START="581" END="584">克什米尔</charseq>
    </name>
    <name>
      <charseq START="603" END="607">克
什米尔</charseq>
    </name>
  </entity_attributes>
</entity>
<entity ID="CTV20001205.1330.0213-E23" TYPE="PER" CLASS="SPC">
  <entity_mention ID="23-67" TYPE="NOM" LDCTYPE="NOM">
    <extent>
      <charseq START="512" END="513">记者</charseq>
    </extent>
    <head>
      <charseq START="512" END="513">记者</charseq>
    </head>
  </entity_mention>
</entity>
<entity ID="CTV20001205.1330.0213-E24" TYPE="ORG" SUBTYPE="Government" CLASS="SPC">
  <entity_mention ID="24-73" TYPE="NOM" LDCTYPE="NOM">
    <extent>
      <charseq START="550" END="559">巴方一侧巴基斯坦军队</charseq>
    </extent>
    <head>
      <charseq START="558" END="559">军队</charseq>
    </head>
  </entity_mention>
</entity>
<entity ID="CTV20001205.1330.0213-E25" TYPE="GPE" SUBTYPE="Nation" CLASS="SPC">
  <entity_mention ID="25-87" TYPE="NOM" LDCTYPE="NOM" ROLE="PER">
    <extent>
      <charseq START="660" END="666">印、巴两国人民</charseq>
    </extent>
    <head>
      <charseq START="665" END="666">人民</charseq>
    </head>
  </entity_mention>
  <entity_mention ID="25-88" TYPE="NOM" LDCTYPE="NOM" ROLE="GPE">
    <extent>
      <charseq START="660" END="664">印、巴两国</charseq>
    </extent>
    <head>
      <charseq START="664" END="664">国</charseq>
    </head>
  </entity_mention>
</entity>
<entity ID="CTV20001205.1330.0213-E26" TYPE="LOC" SUBTYPE="Region-International" CLASS="SPC">
  <entity_mention ID="26-90" TYPE="NOM" LDCTYPE="NOM">
    <extent>
      <charseq START="682" END="685">南亚地区</charseq>
    </extent>
    <head>
      <charseq START="684" END="685">地区</charseq>
    </head>
  </entity_mention>
</entity>
<entity ID="CTV20001205.1330.0213-E27" TYPE="GPE" SUBTYPE="Other" CLASS="SPC">
  <entity_mention ID="27-91" TYPE="NAM" LDCTYPE="NAM" ROLE="LOC">
    <extent>
      <charseq START="682" END="683">南亚</charseq>
    </extent>
    <head>
      <charseq START="682" END="683">南亚</charseq>
    </head>
  </entity_mention>
  <entity_attributes>
    <name>
      <charseq START="682" END="683">南亚</charseq>
    </name>
  </entity_attributes>
</entity>
<entity ID="CTV20001205.1330.0213-E28" TYPE="PER" CLASS="SPC">
  <entity_mention ID="28-92" TYPE="NOM" LDCTYPE="NOM">
    <extent>
      <charseq START="698" END="702">中央台记者</charseq>
    </extent>
    <head>
      <charseq START="701" END="702">记者</charseq>
    </head>
  </entity_mention>
</entity>
<entity ID="CTV20001205.1330.0213-E29" TYPE="ORG" SUBTYPE="Commercial" CLASS="SPC">
  <entity_mention ID="29-94" TYPE="NAM" LDCTYPE="NAM">
    <extent>
      <charseq START="698" END="700">中央台</charseq>
    </extent>
    <head>
      <charseq START="698" END="700">中央台</charseq>
    </head>
  </entity_mention>
  <entity_attributes>
    <name>
      <charseq START="698" END="700">中央台</charseq>
    </name>
  </entity_attributes>
</entity>
<entity ID="CTV20001205.1330.0213-E31" TYPE="GPE" SUBTYPE="Population-Center" CLASS="SPC">
  <entity_mention ID="31-100" TYPE="NAM" LDCTYPE="NAM" ROLE="LOC">
    <extent>
      <charseq START="80" END="86">香港特别行政区</charseq>
    </extent>
    <head>
      <charseq START="80" END="86">香港特别行政区</charseq>
    </head>
  </entity_mention>
  <entity_attributes>
    <name>
      <charseq START="80" END="86">香港特别行政区</charseq>
    </name>
  </entity_attributes>
</entity>
<entity ID="CTV20001205.1330.0213-E32" TYPE="GPE" SUBTYPE="Population-Center" CLASS="SPC">
  <entity_mention ID="32-101" TYPE="NAM" LDCTYPE="NAM" ROLE="LOC">
    <extent>
      <charseq START="96" END="97">北京</charseq>
    </extent>
    <head>
      <charseq START="96" END="97">北京</charseq>
    </head>
  </entity_mention>
  <entity_attributes>
    <name>
      <charseq START="96" END="97">北京</charseq>
    </name>
  </entity_attributes>
</entity>
<entity ID="CTV20001205.1330.0213-E33" TYPE="PER" CLASS="SPC">
  <entity_mention ID="33-12" TYPE="NAM" LDCTYPE="NAM" LDCATR="FALSE">
    <extent>
      <charseq START="217" END="219">张启月</charseq>
    </extent>
    <head>
      <charseq START="217" END="219">张启月</charseq>
    </head>
  </entity_mention>
  <entity_mention ID="33-58" TYPE="NAM" LDCTYPE="NAM" LDCATR="FALSE">
    <extent>
      <charseq START="465" END="467">张启月</charseq>
    </extent>
    <head>
      <charseq START="465" END="467">张启月</charseq>
    </head>
  </entity_mention>
  <entity_mention ID="33-68" TYPE="NAM" LDCTYPE="NAM" LDCATR="FALSE">
    <extent>
      <charseq START="519" END="521">张启月</charseq>
    </extent>
    <head>
      <charseq START="519" END="521">张启月</charseq>
    </head>
  </entity_mention>
  <entity_mention ID="33-103" TYPE="NAM" LDCTYPE="NAM" LDCATR="FALSE">
    <extent>
      <charseq START="107" END="110">张
启月</charseq>
    </extent>
    <head>
      <charseq START="107" END="110">张
启月</charseq>
    </head>
  </entity_mention>
  <entity_mention ID="33-104" TYPE="NOM" LDCTYPE="NOM" LDCATR="TRUE">
    <extent>
      <charseq START="99" END="106">中国外交部发言人</charseq>
    </extent>
    <head>
      <charseq START="104" END="106">发言人</charseq>
    </head>
  </entity_mention>
  <entity_attributes>
    <name>
      <charseq START="217" END="219">张启月</charseq>
    </name>
    <name>
      <charseq START="465" END="467">张启月</charseq>
    </name>
    <name>
      <charseq START="519" END="521">张启月</charseq>
    </name>
    <name>
      <charseq START="107" END="110">张
启月</charseq>
    </name>
  </entity_attributes>
</entity>
<entity ID="CTV20001205.1330.0213-E35" TYPE="ORG" SUBTYPE="Government" CLASS="SPC">
  <entity_mention ID="35-105" TYPE="NAM" LDCTYPE="NAM">
    <extent>
      <charseq START="99" END="103">中国外交部</charseq>
    </extent>
    <head>
      <charseq START="101" END="103">外交部</charseq>
    </head>
  </entity_mention>
  <entity_attributes>
    <name>
      <charseq START="101" END="103">外交部</charseq>
    </name>
  </entity_attributes>
</entity>
<entity ID="CTV20001205.1330.0213-E36" TYPE="GPE" SUBTYPE="Nation" CLASS="SPC">
  <entity_mention ID="36-17" TYPE="NAM" LDCTYPE="NAM" ROLE="LOC">
    <extent>
      <charseq START="248" END="248">华</charseq>
    </extent>
    <head>
      <charseq START="248" END="248">华</charseq>
    </head>
  </entity_mention>
  <entity_mention ID="36-47" TYPE="NAM" LDCTYPE="NAM" ROLE="LOC">
    <extent>
      <charseq START="361" END="361">华</charseq>
    </extent>
    <head>
      <charseq START="361" END="361">华</charseq>
    </head>
  </entity_mention>
  <entity_mention ID="36-69" TYPE="PRO" LDCTYPE="PRO" ROLE="ORG">
    <extent>
      <charseq START="525" END="526">我们</charseq>
    </extent>
    <head>
      <charseq START="525" END="526">我们</charseq>
    </head>
  </entity_mention>
  <entity_mention ID="36-79" TYPE="NOM" LDCTYPE="NOM" ROLE="ORG">
    <extent>
      <charseq START="598" END="601">中国政府</charseq>
    </extent>
    <head>
      <charseq START="600" END="601">政府</charseq>
    </head>
  </entity_mention>
  <entity_mention ID="36-80" TYPE="NAM" LDCTYPE="NAM" ROLE="GPE">
    <extent>
      <charseq START="598" END="599">中国</charseq>
    </extent>
    <head>
      <charseq START="598" END="599">中国</charseq>
    </head>
  </entity_mention>
  <entity_mention ID="36-82" TYPE="PRO" LDCTYPE="PRO" ROLE="ORG">
    <extent>
      <charseq START="622" END="623">我们</charseq>
    </extent>
    <head>
      <charseq START="622" END="623">我们</charseq>
    </head>
  </entity_mention>
  <entity_mention ID="36-106" TYPE="NAM" LDCTYPE="NAM" ROLE="GPE">
    <extent>
      <charseq START="99" END="100">中国</charseq>
    </extent>
    <head>
      <charseq START="99" END="100">中国</charseq>
    </head>
  </entity_mention>
  <entity_mention ID="36-110" TYPE="NAM" LDCTYPE="NAM" ROLE="GPE">
    <extent>
      <charseq START="126" END="127">中国</charseq>
    </extent>
    <head>
      <charseq START="126" END="127">中国</charseq>
    </head>
  </entity_mention>
  <entity_attributes>
    <name>
      <charseq START="248" END="248">华</charseq>
    </name>
    <name>
      <charseq START="361" END="361">华</charseq>
    </name>
    <name>
      <charseq START="598" END="599">中国</charseq>
    </name>
    <name>
      <charseq START="99" END="100">中国</charseq>
    </name>
    <name>
      <charseq START="126" END="127">中国</charseq>
    </name>
  </entity_attributes>
</entity>
<entity ID="CTV20001205.1330.0213-E37" TYPE="PER" CLASS="SPC">
  <entity_mention ID="37-108" TYPE="NAM" LDCTYPE="NAM" LDCATR="FALSE">
    <extent>
      <charseq START="132" END="134">唐家璇</charseq>
    </extent>
    <head>
      <charseq START="132" END="134">唐家璇</charseq>
    </head>
  </entity_mention>
  <entity_mention ID="37-109" TYPE="NOM" LDCTYPE="NOM" LDCATR="TRUE">
    <extent>
      <charseq START="126" END="131">中国外交部长</charseq>
    </extent>
    <head>
      <charseq START="130" END="131">部长</charseq>
    </head>
  </entity_mention>
  <entity_attributes>
    <name>
      <charseq START="132" END="134">唐家璇</charseq>
    </name>
  </entity_attributes>
</entity>
<entity ID="CTV20001205.1330.0213-E39" TYPE="GPE" SUBTYPE="Nation" CLASS="SPC">
  <entity_mention ID="39-11" TYPE="NAM" LDCTYPE="NAM" ROLE="GPE">
    <extent>
      <charseq START="183" END="185">伊拉克</charseq>
    </extent>
    <head>
      <charseq START="183" END="185">伊拉克</charseq>
    </head>
  </entity_mention>
  <entity_mention ID="39-16" TYPE="NAM" LDCTYPE="NAM" ROLE="GPE">
    <extent>
      <charseq START="233" END="235">伊拉克</charseq>
    </extent>
    <head>
      <charseq START="233" END="235">伊拉克</charseq>
    </head>
  </entity_mention>
  <entity_mention ID="39-26" TYPE="NAM" LDCTYPE="NAM" ROLE="GPE">
    <extent>
      <charseq START="279" END="281">伊拉克</charseq>
    </extent>
    <head>
      <charseq START="279" END="281">伊拉克</charseq>
    </head>
  </entity_mention>
  <entity_mention ID="39-46" TYPE="NAM" LDCTYPE="NAM" ROLE="GPE">
    <extent>
      <charseq START="349" END="351">伊拉克</charseq>
    </extent>
    <head>
      <charseq START="349" END="351">伊拉克</charseq>
    </head>
  </entity_mention>
  <entity_mention ID="39-50" TYPE="NAM" LDCTYPE="NAM" ROLE="GPE">
    <extent>
      <charseq START="381" END="383">伊拉克</charseq>
    </extent>
    <head>
      <charseq START="381" END="383">伊拉克</charseq>
    </head>
  </entity_mention>
  <entity_mention ID="39-55" TYPE="NAM" LDCTYPE="NAM" ROLE="GPE">
    <extent>
      <charseq START="413" END="415">伊拉克</charseq>
    </extent>
    <head>
      <charseq START="413" END="415">伊拉克</charseq>
    </head>
  </entity_mention>
  <entity_mention ID="39-57" TYPE="NAM" LDCTYPE="NAM" ROLE="GPE">
    <extent>
      <charseq START="451" END="453">伊拉克</charseq>
    </extent>
    <head>
      <charseq START="451" END="453">伊拉克</charseq>
    </head>
  </entity_mention>
  <entity_mention ID="39-112" TYPE="NAM" LDCTYPE="NAM" ROLE="GPE">
    <extent>
      <charseq START="138" END="140">伊拉克</charseq>
    </extent>
    <head>
      <charseq START="138" END="140">伊拉克</charseq>
    </head>
  </entity_mention>
  <entity_attributes>
    <name>
      <charseq START="183" END="185">伊拉克</charseq>
    </name>
    <name>
      <charseq START="233" END="235">伊拉克</charseq>
    </name>
    <name>
      <charseq START="279" END="281">伊拉克</charseq>
    </name>
    <name>
      <charseq START="349" END="351">伊拉克</charseq>
    </name>
    <name>
      <charseq START="381" END="383">伊拉克</charseq>
    </name>
    <name>
      <charseq START="413" END="415">伊拉克</charseq>
    </name>
    <name>
      <charseq START="451" END="453">伊拉克</charseq>
    </name>
    <name>
      <charseq START="138" END="140">伊拉克</charseq>
    </name>
  </entity_attributes>
</entity>
<entity ID="CTV20001205.1330.0213-E40" TYPE="PER" CLASS="SPC">
  <entity_mention ID="40-43" TYPE="PRO" LDCTYPE="PRO">
    <extent>
      <charseq START="344" END="345">他们</charseq>
    </extent>
    <head>
      <charseq START="344" END="345">他们</charseq>
    </head>
  </entity_mention>
</entity>
<entity ID="CTV20001205.1330.0213-E41" TYPE="PER" CLASS="SPC">
  <entity_mention ID="41-29" TYPE="NOM" LDCTYPE="NOM">
    <extent>
      <charseq START="302" END="329">美国、俄罗斯、英国、法国四个联合国安理会的常任理事国外长</charseq>
    </extent>
    <head>
      <charseq START="328" END="329">外长</charseq>
    </head>
  </entity_mention>
  <entity_mention ID="41-114" TYPE="NOM" LDCTYPE="NOM">
    <extent>
      <charseq START="145" END="171">美国、俄罗斯、英
国、法国这四个安理会常任理事国的外长</charseq>
    </extent>
    <head>
      <charseq START="170" END="171">外长</charseq>
    </head>
  </entity_mention>
</entity>
<relation ID="CTV20001205.1330.0213-R1" TYPE="EMP-ORG" SUBTYPE="Employ-Staff">
  <rel_entity_arg ENTITYID="CTV20001205.1330.0213-E33" ARGNUM="1" />
  <rel_entity_arg ENTITYID="CTV20001205.1330.0213-E35" ARGNUM="2" />
  <relation_mention ID="1-1" LDCLEXICALCONDITION="PreMod">
    <ldc_extent>
      <charseq START="99" END="106">中国外交部发言人</charseq>
    </ldc_extent>
    <rel_mention_arg ENTITYMENTIONID="33-104" ARGNUM="1">
      <extent>
        <charseq START="99" END="106">中国外交部发言人</charseq>
      </extent>
    </rel_mention_arg>
    <rel_mention_arg ENTITYMENTIONID="35-105" ARGNUM="2">
      <extent>
        <charseq START="99" END="103">中国外交部</charseq>
      </extent>
    </rel_mention_arg>
  </relation_mention>
</relation>
<relation ID="CTV20001205.1330.0213-R2" TYPE="EMP-ORG" SUBTYPE="Subsidiary">
  <rel_entity_arg ENTITYID="CTV20001205.1330.0213-E35" ARGNUM="1" />
  <rel_entity_arg ENTITYID="CTV20001205.1330.0213-E36" ARGNUM="2" />
  <relation_mention ID="2-1" LDCLEXICALCONDITION="PreMod">
    <ldc_extent>
      <charseq START="99" END="103">中国外交部</charseq>
    </ldc_extent>
    <rel_mention_arg ENTITYMENTIONID="35-105" ARGNUM="1">
      <extent>
        <charseq START="99" END="103">中国外交部</charseq>
      </extent>
    </rel_mention_arg>
    <rel_mention_arg ENTITYMENTIONID="36-106" ARGNUM="2">
      <extent>
        <charseq START="99" END="100">中国</charseq>
      </extent>
    </rel_mention_arg>
  </relation_mention>
</relation>
<relation ID="CTV20001205.1330.0213-R3" TYPE="EMP-ORG" SUBTYPE="Employ-Staff">
  <rel_entity_arg ENTITYID="CTV20001205.1330.0213-E37" ARGNUM="1" />
  <rel_entity_arg ENTITYID="CTV20001205.1330.0213-E36" ARGNUM="2" />
  <relation_mention ID="3-1" LDCLEXICALCONDITION="PreMod">
    <ldc_extent>
      <charseq START="126" END="131">中国外交部长</charseq>
    </ldc_extent>
    <rel_mention_arg ENTITYMENTIONID="37-109" ARGNUM="1">
      <extent>
        <charseq START="126" END="131">中国外交部长</charseq>
      </extent>
    </rel_mention_arg>
    <rel_mention_arg ENTITYMENTIONID="36-110" ARGNUM="2">
      <extent>
        <charseq START="126" END="127">中国</charseq>
      </extent>
    </rel_mention_arg>
  </relation_mention>
</relation>
<relation ID="CTV20001205.1330.0213-R4" TYPE="EMP-ORG" SUBTYPE="Employ-Staff">
  <rel_entity_arg ENTITYID="CTV20001205.1330.0213-E41" ARGNUM="1" />
  <rel_entity_arg ENTITYID="CTV20001205.1330.0213-E12" ARGNUM="2" />
  <relation_mention ID="4-1" LDCLEXICALCONDITION="PreMod">
    <ldc_extent>
      <charseq START="145" END="171">美国、俄罗斯、英
国、法国这四个安理会常任理事国的外长</charseq>
    </ldc_extent>
    <rel_mention_arg ENTITYMENTIONID="41-114" ARGNUM="1">
      <extent>
        <charseq START="145" END="171">美国、俄罗斯、英
国、法国这四个安理会常任理事国的外长</charseq>
      </extent>
    </rel_mention_arg>
    <rel_mention_arg ENTITYMENTIONID="12-115" ARGNUM="2">
      <extent>
        <charseq START="158" END="168">这四个安理会常任理事国</charseq>
      </extent>
    </rel_mention_arg>
  </relation_mention>
  <relation_mention ID="4-2" LDCLEXICALCONDITION="PreMod">
    <ldc_extent>
      <charseq START="302" END="329">美国、俄罗斯、英国、法国四个联合国安理会的常任理事国外长</charseq>
    </ldc_extent>
    <rel_mention_arg ENTITYMENTIONID="41-29" ARGNUM="1">
      <extent>
        <charseq START="302" END="329">美国、俄罗斯、英国、法国四个联合国安理会的常任理事国外长</charseq>
      </extent>
    </rel_mention_arg>
    <rel_mention_arg ENTITYMENTIONID="12-30" ARGNUM="2">
      <extent>
        <charseq START="302" END="327">美国、俄罗斯、英国、法国四个联合国安理会的常任理事国</charseq>
      </extent>
    </rel_mention_arg>
  </relation_mention>
</relation>
<relation ID="CTV20001205.1330.0213-R5" TYPE="EMP-ORG" SUBTYPE="Employ-Executive">
  <rel_entity_arg ENTITYID="CTV20001205.1330.0213-E5" ARGNUM="1" />
  <rel_entity_arg ENTITYID="CTV20001205.1330.0213-E7" ARGNUM="2" />
  <relation_mention ID="5-1" LDCLEXICALCONDITION="PreMod">
    <ldc_extent>
      <charseq START="173" END="178">联合国秘书长</charseq>
    </ldc_extent>
    <rel_mention_arg ENTITYMENTIONID="5-9" ARGNUM="1">
      <extent>
        <charseq START="173" END="178">联合国秘书长</charseq>
      </extent>
    </rel_mention_arg>
    <rel_mention_arg ENTITYMENTIONID="7-10" ARGNUM="2">
      <extent>
        <charseq START="173" END="175">联合国</charseq>
      </extent>
    </rel_mention_arg>
  </relation_mention>
  <relation_mention ID="5-2" LDCLEXICALCONDITION="PreMod">
    <ldc_extent>
      <charseq START="333" END="339">联
合国秘书长</charseq>
    </ldc_extent>
    <rel_mention_arg ENTITYMENTIONID="5-95" ARGNUM="1">
      <extent>
        <charseq START="333" END="339">联
合国秘书长</charseq>
      </extent>
    </rel_mention_arg>
    <rel_mention_arg ENTITYMENTIONID="7-42" ARGNUM="2">
      <extent>
        <charseq START="333" END="336">联
合国</charseq>
      </extent>
    </rel_mention_arg>
  </relation_mention>
  <relation_mention ID="5-3" LDCLEXICALCONDITION="PreMod">
    <ldc_extent>
      <charseq START="402" END="407">联合国秘书长</charseq>
    </ldc_extent>
    <rel_mention_arg ENTITYMENTIONID="5-53" ARGNUM="1">
      <extent>
        <charseq START="402" END="407">联合国秘书长</charseq>
      </extent>
    </rel_mention_arg>
    <rel_mention_arg ENTITYMENTIONID="7-54" ARGNUM="2">
      <extent>
        <charseq START="402" END="404">联合国</charseq>
      </extent>
    </rel_mention_arg>
  </relation_mention>
</relation>
<relation ID="CTV20001205.1330.0213-R6" TYPE="EMP-ORG" SUBTYPE="Employ-Executive">
  <rel_entity_arg ENTITYID="CTV20001205.1330.0213-E20" ARGNUM="1" />
  <rel_entity_arg ENTITYID="CTV20001205.1330.0213-E39" ARGNUM="2" />
  <relation_mention ID="6-1" LDCLEXICALCONDITION="PreMod">
    <ldc_extent>
      <charseq START="233" END="238">伊拉克副总理</charseq>
    </ldc_extent>
    <rel_mention_arg ENTITYMENTIONID="20-15" ARGNUM="1">
      <extent>
        <charseq START="233" END="238">伊拉克副总理</charseq>
      </extent>
    </rel_mention_arg>
    <rel_mention_arg ENTITYMENTIONID="39-16" ARGNUM="2">
      <extent>
        <charseq START="233" END="235">伊拉克</charseq>
      </extent>
    </rel_mention_arg>
  </relation_mention>
  <relation_mention ID="6-2" LDCLEXICALCONDITION="PreMod">
    <ldc_extent>
      <charseq START="349" END="354">伊拉克副总理</charseq>
    </ldc_extent>
    <rel_mention_arg ENTITYMENTIONID="20-96" ARGNUM="1">
      <extent>
        <charseq START="349" END="354">伊拉克副总理</charseq>
      </extent>
    </rel_mention_arg>
    <rel_mention_arg ENTITYMENTIONID="39-46" ARGNUM="2">
      <extent>
        <charseq START="349" END="351">伊拉克</charseq>
      </extent>
    </rel_mention_arg>
  </relation_mention>
</relation>
<relation ID="CTV20001205.1330.0213-R8" TYPE="DISC">
  <rel_entity_arg ENTITYID="CTV20001205.1330.0213-E1" ARGNUM="1" />
  <rel_entity_arg ENTITYID="CTV20001205.1330.0213-E12" ARGNUM="2" />
  <relation_mention ID="8-1" LDCLEXICALCONDITION="PreMod">
    <ldc_extent>
      <charseq START="302" END="327">美国、俄罗斯、英国、法国四个联合国安理会的常任理事国</charseq>
    </ldc_extent>
    <rel_mention_arg ENTITYMENTIONID="1-32" ARGNUM="1">
      <extent>
        <charseq START="302" END="303">美国</charseq>
      </extent>
    </rel_mention_arg>
    <rel_mention_arg ENTITYMENTIONID="12-30" ARGNUM="2">
      <extent>
        <charseq START="302" END="327">美国、俄罗斯、英国、法国四个联合国安理会的常任理事国</charseq>
      </extent>
    </rel_mention_arg>
  </relation_mention>
</relation>
<relation ID="CTV20001205.1330.0213-R9" TYPE="DISC">
  <rel_entity_arg ENTITYID="CTV20001205.1330.0213-E2" ARGNUM="1" />
  <rel_entity_arg ENTITYID="CTV20001205.1330.0213-E12" ARGNUM="2" />
  <relation_mention ID="9-1" LDCLEXICALCONDITION="PreMod">
    <ldc_extent>
      <charseq START="302" END="327">美国、俄罗斯、英国、法国四个联合国安理会的常任理事国</charseq>
    </ldc_extent>
    <rel_mention_arg ENTITYMENTIONID="2-33" ARGNUM="1">
      <extent>
        <charseq START="305" END="307">俄罗斯</charseq>
      </extent>
    </rel_mention_arg>
    <rel_mention_arg ENTITYMENTIONID="12-30" ARGNUM="2">
      <extent>
        <charseq START="302" END="327">美国、俄罗斯、英国、法国四个联合国安理会的常任理事国</charseq>
      </extent>
    </rel_mention_arg>
  </relation_mention>
</relation>
<relation ID="CTV20001205.1330.0213-R10" TYPE="DISC">
  <rel_entity_arg ENTITYID="CTV20001205.1330.0213-E3" ARGNUM="1" />
  <rel_entity_arg ENTITYID="CTV20001205.1330.0213-E12" ARGNUM="2" />
  <relation_mention ID="10-1" LDCLEXICALCONDITION="PreMod">
    <ldc_extent>
      <charseq START="302" END="327">美国、俄罗斯、英国、法国四个联合国安理会的常任理事国</charseq>
    </ldc_extent>
    <rel_mention_arg ENTITYMENTIONID="3-34" ARGNUM="1">
      <extent>
        <charseq START="309" END="310">英国</charseq>
      </extent>
    </rel_mention_arg>
    <rel_mention_arg ENTITYMENTIONID="12-30" ARGNUM="2">
      <extent>
        <charseq START="302" END="327">美国、俄罗斯、英国、法国四个联合国安理会的常任理事国</charseq>
      </extent>
    </rel_mention_arg>
  </relation_mention>
</relation>
<relation ID="CTV20001205.1330.0213-R11" TYPE="DISC">
  <rel_entity_arg ENTITYID="CTV20001205.1330.0213-E4" ARGNUM="1" />
  <rel_entity_arg ENTITYID="CTV20001205.1330.0213-E12" ARGNUM="2" />
  <relation_mention ID="11-1" LDCLEXICALCONDITION="PreMod">
    <ldc_extent>
      <charseq START="302" END="327">美国、俄罗斯、英国、法国四个联合国安理会的常任理事国</charseq>
    </ldc_extent>
    <rel_mention_arg ENTITYMENTIONID="4-35" ARGNUM="1">
      <extent>
        <charseq START="312" END="313">法国</charseq>
      </extent>
    </rel_mention_arg>
    <rel_mention_arg ENTITYMENTIONID="12-30" ARGNUM="2">
      <extent>
        <charseq START="302" END="327">美国、俄罗斯、英国、法国四个联合国安理会的常任理事国</charseq>
      </extent>
    </rel_mention_arg>
  </relation_mention>
  <relation_mention ID="11-2" LDCLEXICALCONDITION="PreMod">
    <ldc_extent>
      <charseq START="302" END="327">美国、俄罗斯、英国、法国四个联合国安理会的常任理事国</charseq>
    </ldc_extent>
    <rel_mention_arg ENTITYMENTIONID="4-35" ARGNUM="1">
      <extent>
        <charseq START="312" END="313">法国</charseq>
      </extent>
    </rel_mention_arg>
    <rel_mention_arg ENTITYMENTIONID="12-30" ARGNUM="2">
      <extent>
        <charseq START="302" END="327">美国、俄罗斯、英国、法国四个联合国安理会的常任理事国</charseq>
      </extent>
    </rel_mention_arg>
  </relation_mention>
</relation>
<relation ID="CTV20001205.1330.0213-R16" TYPE="DISC">
  <rel_entity_arg ENTITYID="CTV20001205.1330.0213-E19" ARGNUM="1" />
  <rel_entity_arg ENTITYID="CTV20001205.1330.0213-E18" ARGNUM="2" />
  <relation_mention ID="16-1" LDCLEXICALCONDITION="PreMod">
    <ldc_extent>
      <charseq START="470" END="481">印、巴和克什米尔地区三方</charseq>
    </ldc_extent>
    <rel_mention_arg ENTITYMENTIONID="19-62" ARGNUM="1">
      <extent>
        <charseq START="470" END="470">印</charseq>
      </extent>
    </rel_mention_arg>
    <rel_mention_arg ENTITYMENTIONID="18-97" ARGNUM="2">
      <extent>
        <charseq START="470" END="481">印、巴和克什米尔地区三方</charseq>
      </extent>
    </rel_mention_arg>
  </relation_mention>
</relation>
<relation ID="CTV20001205.1330.0213-R17" TYPE="DISC">
  <rel_entity_arg ENTITYID="CTV20001205.1330.0213-E21" ARGNUM="1" />
  <rel_entity_arg ENTITYID="CTV20001205.1330.0213-E18" ARGNUM="2" />
  <relation_mention ID="17-1" LDCLEXICALCONDITION="PreMod">
    <ldc_extent>
      <charseq START="470" END="481">印、巴和克什米尔地区三方</charseq>
    </ldc_extent>
    <rel_mention_arg ENTITYMENTIONID="21-63" ARGNUM="1">
      <extent>
        <charseq START="472" END="472">巴</charseq>
      </extent>
    </rel_mention_arg>
    <rel_mention_arg ENTITYMENTIONID="18-97" ARGNUM="2">
      <extent>
        <charseq START="470" END="481">印、巴和克什米尔地区三方</charseq>
      </extent>
    </rel_mention_arg>
  </relation_mention>
</relation>
<relation ID="CTV20001205.1330.0213-R18" TYPE="DISC">
  <rel_entity_arg ENTITYID="CTV20001205.1330.0213-E22" ARGNUM="1" />
  <rel_entity_arg ENTITYID="CTV20001205.1330.0213-E18" ARGNUM="2" />
  <relation_mention ID="18-1" LDCLEXICALCONDITION="PreMod">
    <ldc_extent>
      <charseq START="470" END="481">印、巴和克什米尔地区三方</charseq>
    </ldc_extent>
    <rel_mention_arg ENTITYMENTIONID="22-64" ARGNUM="1">
      <extent>
        <charseq START="474" END="479">克什米尔地区</charseq>
      </extent>
    </rel_mention_arg>
    <rel_mention_arg ENTITYMENTIONID="18-97" ARGNUM="2">
      <extent>
        <charseq START="470" END="481">印、巴和克什米尔地区三方</charseq>
      </extent>
    </rel_mention_arg>
  </relation_mention>
</relation>
<relation ID="CTV20001205.1330.0213-R19" TYPE="EMP-ORG" SUBTYPE="Subsidiary">
  <rel_entity_arg ENTITYID="CTV20001205.1330.0213-E24" ARGNUM="1" />
  <rel_entity_arg ENTITYID="CTV20001205.1330.0213-E21" ARGNUM="2" />
  <relation_mention ID="19-1" LDCLEXICALCONDITION="PreMod">
    <ldc_extent>
      <charseq START="550" END="559">巴方一侧巴基斯坦军队</charseq>
    </ldc_extent>
    <rel_mention_arg ENTITYMENTIONID="24-73" ARGNUM="1">
      <extent>
        <charseq START="550" END="559">巴方一侧巴基斯坦军队</charseq>
      </extent>
    </rel_mention_arg>
    <rel_mention_arg ENTITYMENTIONID="21-75" ARGNUM="2">
      <extent>
        <charseq START="550" END="551">巴方</charseq>
      </extent>
    </rel_mention_arg>
  </relation_mention>
</relation>
<relation ID="CTV20001205.1330.0213-R20" TYPE="DISC">
  <rel_entity_arg ENTITYID="CTV20001205.1330.0213-E19" ARGNUM="1" />
  <rel_entity_arg ENTITYID="CTV20001205.1330.0213-E25" ARGNUM="2" />
  <relation_mention ID="20-1" LDCLEXICALCONDITION="PreMod">
    <ldc_extent>
      <charseq START="660" END="664">印、巴两国</charseq>
    </ldc_extent>
    <rel_mention_arg ENTITYMENTIONID="19-98" ARGNUM="1">
      <extent>
        <charseq START="660" END="660">印</charseq>
      </extent>
    </rel_mention_arg>
    <rel_mention_arg ENTITYMENTIONID="25-88" ARGNUM="2">
      <extent>
        <charseq START="660" END="664">印、巴两国</charseq>
      </extent>
    </rel_mention_arg>
  </relation_mention>
</relation>
<relation ID="CTV20001205.1330.0213-R21" TYPE="DISC">
  <rel_entity_arg ENTITYID="CTV20001205.1330.0213-E21" ARGNUM="1" />
  <rel_entity_arg ENTITYID="CTV20001205.1330.0213-E25" ARGNUM="2" />
  <relation_mention ID="21-1" LDCLEXICALCONDITION="PreMod">
    <ldc_extent>
      <charseq START="660" END="664">印、巴两国</charseq>
    </ldc_extent>
    <rel_mention_arg ENTITYMENTIONID="21-99" ARGNUM="1">
      <extent>
        <charseq START="662" END="662">巴</charseq>
      </extent>
    </rel_mention_arg>
    <rel_mention_arg ENTITYMENTIONID="25-88" ARGNUM="2">
      <extent>
        <charseq START="660" END="664">印、巴两国</charseq>
      </extent>
    </rel_mention_arg>
  </relation_mention>
</relation>
</document>
</source_file>
